{
  "skill": "heartbeat-pulse-check",
  "run_at": "2026-06-24T21:00:03.364610+00:00",
  "target_date": "2026-06-24",
  "verdict": "YELLOW",
  "reason": "4-gaps-6-to-15-min",
  "fire_count_total": 112,
  "market_fire_count": 112,
  "max_gap_minutes": 8.98,
  "gaps_over_15_min": 0,
  "gaps_6_to_15_min": 4,
  "heal_action": "no-op",
  "sample_gaps": [
    {
      "from": "09:40:01",
      "to": "09:45:02",
      "gap_min": 5.02
    },
    {
      "from": "09:54:01",
      "to": "09:59:01",
      "gap_min": 5.0
    },
    {
      "from": "09:59:01",
      "to": "10:03:02",
      "gap_min": 4.02
    },
    {
      "from": "10:06:02",
      "to": "10:11:01",
      "gap_min": 4.98
    },
    {
      "from": "10:11:01",
      "to": "10:15:02",
      "gap_min": 4.02
    },
    {
      "from": "10:21:02",
      "to": "10:29:01",
      "gap_min": 7.98
    },
    {
      "from": "10:29:01",
      "to": "10:33:02",
      "gap_min": 4.02
    },
    {
      "from": "10:42:02",
      "to": "10:48:02",
      "gap_min": 6.0
    },
    {
      "from": "10:51:02",
      "to": "10:57:01",
      "gap_min": 5.98
    },
    {
      "from": "10:57:01",
      "to": "11:03:02",
      "gap_min": 6.02
    }
  ]
}